annotree/__init__.py
annotree/__main__.py
annotree/annotree.py
annotree-0.2.0.dist-info/METADATA
annotree-0.2.0.dist-info/WHEEL
annotree-0.2.0.dist-info/entry_points.txt
annotree-0.2.0.dist-info/licenses/LICENSE
annotree-0.2.0.dist-info/RECORD
