Metadata-Version: 2.4
Name: annotree
Version: 0.2.0
Summary: Generate annotated file tree structures with descriptions from file comments
Project-URL: Homepage, https://github.com/suecrumpler/annotree
Project-URL: Documentation, https://github.com/suecrumpler/annotree#readme
Project-URL: Bug Reports, https://github.com/suecrumpler/annotree/issues
Project-URL: Source, https://github.com/suecrumpler/annotree
Author-email: Sue Crumpler <sue.crumpler123@gmail.com>
License-Expression: MIT
License-File: LICENSE
Keywords: annotations,directory,documentation,gitignore,structure,tree,treeignore
Classifier: Development Status :: 3 - Alpha
Classifier: Intended Audience :: Developers
Classifier: Programming Language :: Python :: 3
Classifier: Programming Language :: Python :: 3.8
Classifier: Programming Language :: Python :: 3.9
Classifier: Programming Language :: Python :: 3.10
Classifier: Programming Language :: Python :: 3.11
Classifier: Programming Language :: Python :: 3.12
Classifier: Topic :: Software Development :: Documentation
Classifier: Topic :: Utilities
Requires-Python: >=3.8
Requires-Dist: gitignore-parser>=0.1.0
